owa/cli/__init__.py
owa/cli/__main__.py
owa/cli/click_compat.py
owa/cli/console.py
owa/cli/utils.py
owa/cli/window.py
owa/cli/env/__init__.py
owa/cli/env/click_compat.py
owa/cli/env/docs.py
owa/cli/env/list.py
owa/cli/env/search.py
owa/cli/env/stats.py
owa/cli/env/validate.py
owa/cli/mcap/__init__.py
owa/cli/mcap/cat.py
owa/cli/mcap/click_compat.py
owa/cli/mcap/info.py
owa/cli/mcap/rename_uri.py
owa/cli/mcap/sanitize.py
owa/cli/mcap/subtitle.py
owa/cli/mcap/migrate/__init__.py
owa/cli/mcap/migrate/cleanup.py
owa/cli/mcap/migrate/file_utils.py
owa/cli/mcap/migrate/migrate.py
owa/cli/mcap/migrate/rollback.py
owa/cli/mcap/migrate/schemas.json
owa/cli/mcap/migrate/utils.py
owa/cli/mcap/migrate/migrators/README.md
owa/cli/mcap/migrate/migrators/v0_2_0_to_v0_3_0.py
owa/cli/mcap/migrate/migrators/v0_3_0_to_v0_3_2.py
owa/cli/mcap/migrate/migrators/v0_3_2_to_v0_4_2.py
owa/cli/mcap/migrate/migrators/v0_4_2_to_v0_5_0.py
owa/cli/mcap/migrate/migrators/v0_5_0_to_v0_5_1.py
owa/cli/mcap/migrate/migrators/v0_5_1_to_v0_5_5.py
owa/cli/mcap/migrate/migrators/v0_5_5_to_v0_5_6.py
owa/cli/messages/__init__.py
owa/cli/messages/click_compat.py
owa/cli/messages/list.py
owa/cli/messages/show.py
owa/cli/messages/validate.py
owa/cli/video/__init__.py
owa/cli/video/click_compat.py
owa/cli/video/probe.py
owa/cli/video/transcode.py
owa/cli/video/vfr_to_cfr.py
owa_cli-0.6.5.dist-info/METADATA
owa_cli-0.6.5.dist-info/WHEEL
owa_cli-0.6.5.dist-info/entry_points.txt
owa_cli-0.6.5.dist-info/RECORD
