Metadata-Version: 2.4
Name: owa-cli
Version: 0.6.5
Summary: Command-line tools for Open World Agents data analysis and management
License: MIT
Requires-Python: >=3.11
Requires-Dist: loguru
Requires-Dist: mcap-owa-support==0.6.5
Requires-Dist: mediaref~=0.4.1
Requires-Dist: numpy>=2.0
Requires-Dist: opencv-python
Requires-Dist: orjson
Requires-Dist: owa-core==0.6.5
Requires-Dist: owa-msgs==0.6.5
Requires-Dist: packaging>=20.0
Requires-Dist: plotext
Requires-Dist: pyyaml>=6.0
Requires-Dist: requests>=2.32.2
Requires-Dist: rich>=14.1.0
Requires-Dist: tqdm
Requires-Dist: typer>=0.20.0
